LICENSE
README.md
setup.py
fourbars/__init__.py
fourbars.egg-info/PKG-INFO
fourbars.egg-info/SOURCES.txt
fourbars.egg-info/dependency_links.txt
fourbars.egg-info/requires.txt
fourbars.egg-info/top_level.txt