Metadata-Version: 2.1
Name: fourbars
Version: 1.0.91
Summary: Ableton Live CLI - High Precision Loop Production and Asset Management
Home-page: https://github.com/styk-tv/4bars
Author: Peter Styk
Author-email: dev@4bars.media
License: UNKNOWN
Keywords: sound,music,ableton,osc,pylive
Platform: UNKNOWN
Classifier: Topic :: Multimedia :: Sound/Audio
Classifier: Topic :: Artistic Software
Classifier: Topic :: Communications
Classifier: Development Status :: 4 - Beta
Classifier: Intended Audience :: Developers
License-File: LICENSE
